klondike_spec_cli/__init__.py
klondike_spec_cli/__main__.py
klondike_spec_cli/_version.py
klondike_spec_cli/cli.py
klondike_spec_cli/completion.py
klondike_spec_cli/copilot.py
klondike_spec_cli/data.py
klondike_spec_cli/formatting.py
klondike_spec_cli/git.py
klondike_spec_cli/mcp_server.py
klondike_spec_cli/models.py
klondike_spec_cli/ntfy.py
klondike_spec_cli/validation.py
klondike_spec_cli/worktree.py
klondike_spec_cli/agents/__init__.py
klondike_spec_cli/agents/base.py
klondike_spec_cli/agents/claude.py
klondike_spec_cli/agents/copilot.py
klondike_spec_cli/commands/__init__.py
klondike_spec_cli/commands/admin.py
klondike_spec_cli/commands/agents_cmd.py
klondike_spec_cli/commands/copilot_cmd.py
klondike_spec_cli/commands/features.py
klondike_spec_cli/commands/init.py
klondike_spec_cli/commands/io.py
klondike_spec_cli/commands/mcp_cmd.py
klondike_spec_cli/commands/release_cmd.py
klondike_spec_cli/commands/reporting.py
klondike_spec_cli/commands/serve_cmd.py
klondike_spec_cli/commands/sessions.py
klondike_spec_cli/static/index.html
klondike_spec_cli/static/klondike.svg
klondike_spec_cli/static/sw.js
klondike_spec_cli/static/vite.svg
klondike_spec_cli/static/assets/index-BXLHEC1W.js
klondike_spec_cli/static/assets/index-ym0h-tiF.css
klondike_spec_cli/templates/__init__.py
klondike_spec_cli/templates/agent-progress.json
klondike_spec_cli/templates/config.yaml
klondike_spec_cli/templates/features.json
klondike_spec_cli/templates/claude_templates/CLAUDE.md
klondike_spec_cli/templates/claude_templates/__init__.py
klondike_spec_cli/templates/claude_templates/settings.json
klondike_spec_cli/templates/claude_templates/commands/__init__.py
klondike_spec_cli/templates/claude_templates/commands/add-features.md
klondike_spec_cli/templates/claude_templates/commands/continuous-implementation.md
klondike_spec_cli/templates/claude_templates/commands/init-and-build.md
klondike_spec_cli/templates/claude_templates/commands/init-project.md
klondike_spec_cli-1.0.13.dist-info/METADATA
klondike_spec_cli-1.0.13.dist-info/WHEEL
klondike_spec_cli-1.0.13.dist-info/entry_points.txt
klondike_spec_cli-1.0.13.dist-info/licenses/LICENSE
klondike_spec_cli-1.0.13.dist-info/RECORD
