Metadata-Version: 2.4
Name: klondike-spec-cli
Version: 1.0.13
Summary: CLI tool for managing Klondike Spec agent workflow artifacts
Project-URL: Homepage, https://github.com/ThomasRohde/klondike-spec-cli
Project-URL: Repository, https://github.com/ThomasRohde/klondike-spec-cli
Project-URL: Issues, https://github.com/ThomasRohde/klondike-spec-cli/issues
Author: Thomas Rohde
License-Expression: MIT
License-File: LICENSE
Keywords: agent,cli,copilot,klondike-spec,workflow
Classifier: Development Status :: 3 - Alpha
Classifier: Environment :: Console
Classifier: Intended Audience :: Developers
Classifier: License :: OSI Approved :: MIT License
Classifier: Operating System :: OS Independent
Classifier: Programming Language :: Python :: 3
Classifier: Programming Language :: Python :: 3.10
Classifier: Programming Language :: Python :: 3.11
Classifier: Programming Language :: Python :: 3.12
Classifier: Topic :: Software Development :: Build Tools
Classifier: Topic :: Software Development :: Quality Assurance
Requires-Python: >=3.10
Requires-Dist: fastapi>=0.115.0
Requires-Dist: mcp>=1.2.0
Requires-Dist: pypith>=0.1.2
Requires-Dist: pyyaml>=6.0
Requires-Dist: requests>=2.31.0
Requires-Dist: rich>=13.0
Requires-Dist: uvicorn[standard]>=0.32.0
Requires-Dist: watchdog>=3.0.0
Requires-Dist: websockets<15
Provides-Extra: dev
Requires-Dist: mypy>=1.0; extra == 'dev'
Requires-Dist: pytest-cov>=4.0; extra == 'dev'
Requires-Dist: pytest>=8.0; extra == 'dev'
Requires-Dist: ruff>=0.1.0; extra == 'dev'
Requires-Dist: types-pyyaml>=6.0; extra == 'dev'
